{
  "appearances": {
    "primary": {
      "name": "tira red",
      "baseStep": 1600,
      "darkerBaseStep": 1700,
      "palette": {
        "100": "#000000",
        "200": "#000000",
        "300": "#070100",
        "400": "#170000",
        "500": "#270000",
        "600": "#390000",
        "700": "#490000",
        "800": "#5B0000",
        "900": "#6E0000",
        "1000": "#810000",
        "1100": "#940000",
        "1200": "#A90000",
        "1300": "#BD0000",
        "1400": "#D10000",
        "1500": "#E80200",
        "1600": "#F11A00",
        "1700": "#FF3B25",
        "1800": "#FF6651",
        "1900": "#FF826E",
        "2000": "#FF9886",
        "2100": "#FFAFA3",
        "2200": "#FFC5BB",
        "2300": "#F9DBD7",
        "2400": "#F5F0F0",
        "2500": "#FFFFFF"
      },
      "anchorBoldToBaseStep": true
    },
    "secondary": {
      "name": "blue",
      "baseStep": 1300,
      "darkerBaseStep": 1400,
      "palette": {
        "100": "#000000",
        "200": "#00001F",
        "300": "#01003A",
        "400": "#02004D",
        "500": "#030061",
        "600": "#00007A",
        "700": "#00038A",
        "800": "#001795",
        "900": "#0028A2",
        "1000": "#0334AD",
        "1100": "#0D3FB9",
        "1200": "#1C50CA",
        "1300": "#2257D1",
        "1400": "#2D64DF",
        "1500": "#3A72EF",
        "1600": "#457FFD",
        "1700": "#588EFF",
        "1800": "#6D9EFF",
        "1900": "#82ACFF",
        "2000": "#95BAFF",
        "2100": "#A9CAFF",
        "2200": "#BFD7FF",
        "2300": "#D8E4F7",
        "2400": "#F0F2F5",
        "2500": "#FFFFFF"
      },
      "anchorBoldToBaseStep": true
    },
    "sparkle": {
      "name": "light grayish red",
      "baseStep": 1500,
      "darkerBaseStep": 1600,
      "palette": {
        "100": "#000000",
        "200": "#200903",
        "300": "#291107",
        "400": "#30170E",
        "500": "#371E14",
        "600": "#40251C",
        "700": "#482C23",
        "800": "#4F332A",
        "900": "#583C32",
        "1000": "#604339",
        "1100": "#684A41",
        "1200": "#725349",
        "1300": "#7A5B51",
        "1400": "#86665C",
        "1500": "#947469",
        "1600": "#A07F75",
        "1700": "#AD8C81",
        "1800": "#BB998E",
        "1900": "#C8A69A",
        "2000": "#D5B3A7",
        "2100": "#E5C1B6",
        "2200": "#F4D0C4",
        "2300": "#F8DED6",
        "2400": "#FDF0EC",
        "2500": "#FFFFFF"
      },
      "anchorBoldToBaseStep": true
    },
    "brand-bg": {
      "name": "orange",
      "baseStep": 1300,
      "darkerBaseStep": 1400,
      "palette": {
        "100": "#000000",
        "200": "#1A0801",
        "300": "#2E1100",
        "400": "#401A00",
        "500": "#532400",
        "600": "#662D00",
        "700": "#773701",
        "800": "#8A4001",
        "900": "#9B4800",
        "1000": "#AA5000",
        "1100": "#B95800",
        "1200": "#C86001",
        "1300": "#D86801",
        "1400": "#E56F00",
        "1500": "#F47600",
        "1600": "#FA7D19",
        "1700": "#FD8B40",
        "1800": "#FF9E61",
        "1900": "#FFAF7F",
        "2000": "#FFBD97",
        "2100": "#FFCBAD",
        "2200": "#FFD8C3",
        "2300": "#FFE5D7",
        "2400": "#FFF2EB",
        "2500": "#FFFFFF"
      },
      "anchorBoldToBaseStep": true
    },
    "neutral": {
      "name": "Neutral",
      "baseStep": 1300,
      "darkerBaseStep": 1400,
      "palette": {
        "100": "#000000",
        "200": "#000000",
        "300": "#020202",
        "400": "#060606",
        "500": "#0E0E0E",
        "600": "#181818",
        "700": "#222222",
        "800": "#2B2B2B",
        "900": "#373737",
        "1000": "#414141",
        "1100": "#4C4C4C",
        "1200": "#585858",
        "1300": "#636363",
        "1400": "#6E6F6F",
        "1500": "#808080",
        "1600": "#878788",
        "1700": "#949494",
        "1800": "#A1A1A1",
        "1900": "#AEAEAE",
        "2000": "#BABABA",
        "2100": "#C9C9C9",
        "2200": "#D6D6D6",
        "2300": "#E3E3E3",
        "2400": "#F2F2F2",
        "2500": "#FFFFFF"
      }
    },
    "positive": {
      "name": "green",
      "baseStep": 1600,
      "darkerBaseStep": 1700,
      "palette": {
        "100": "#000000",
        "200": "#000000",
        "300": "#000300",
        "400": "#000A00",
        "500": "#001500",
        "600": "#002000",
        "700": "#002C00",
        "800": "#003700",
        "900": "#004500",
        "1000": "#005100",
        "1100": "#005E00",
        "1200": "#006C02",
        "1300": "#007A04",
        "1400": "#008805",
        "1500": "#00970A",
        "1600": "#00A50D",
        "1700": "#00B31B",
        "1800": "#28C332",
        "1900": "#3ACF40",
        "2000": "#4BDC4F",
        "2100": "#67EB57",
        "2200": "#7FF670",
        "2300": "#B3F8AA",
        "2400": "#EBF5EA",
        "2500": "#FFFFFF"
      }
    },
    "negative": {
      "name": "tira red",
      "baseStep": 1300,
      "darkerBaseStep": 1400,
      "palette": {
        "100": "#000000",
        "200": "#000000",
        "300": "#070100",
        "400": "#170000",
        "500": "#270000",
        "600": "#390000",
        "700": "#490000",
        "800": "#5B0000",
        "900": "#6E0000",
        "1000": "#810000",
        "1100": "#940000",
        "1200": "#A90000",
        "1300": "#BD0000",
        "1400": "#D10000",
        "1500": "#E80200",
        "1600": "#F11A00",
        "1700": "#FF3B25",
        "1800": "#FF6651",
        "1900": "#FF826E",
        "2000": "#FF9886",
        "2100": "#FFAFA3",
        "2200": "#FFC5BB",
        "2300": "#F9DBD7",
        "2400": "#F5F0F0",
        "2500": "#FFFFFF"
      }
    },
    "warning": {
      "name": "orange",
      "baseStep": 1300,
      "darkerBaseStep": 1400,
      "palette": {
        "100": "#000000",
        "200": "#1A0801",
        "300": "#2E1100",
        "400": "#401A00",
        "500": "#532400",
        "600": "#662D00",
        "700": "#773701",
        "800": "#8A4001",
        "900": "#9B4800",
        "1000": "#AA5000",
        "1100": "#B95800",
        "1200": "#C86001",
        "1300": "#D86801",
        "1400": "#E56F00",
        "1500": "#F47600",
        "1600": "#FA7D19",
        "1700": "#FD8B40",
        "1800": "#FF9E61",
        "1900": "#FFAF7F",
        "2000": "#FFBD97",
        "2100": "#FFCBAD",
        "2200": "#FFD8C3",
        "2300": "#FFE5D7",
        "2400": "#FFF2EB",
        "2500": "#FFFFFF"
      }
    },
    "informative": {
      "name": "blue",
      "baseStep": 1300,
      "darkerBaseStep": 1400,
      "palette": {
        "100": "#000000",
        "200": "#00001F",
        "300": "#01003A",
        "400": "#02004D",
        "500": "#030061",
        "600": "#00007A",
        "700": "#00038A",
        "800": "#001795",
        "900": "#0028A2",
        "1000": "#0334AD",
        "1100": "#0D3FB9",
        "1200": "#1C50CA",
        "1300": "#2257D1",
        "1400": "#2D64DF",
        "1500": "#3A72EF",
        "1600": "#457FFD",
        "1700": "#588EFF",
        "1800": "#6D9EFF",
        "1900": "#82ACFF",
        "2000": "#95BAFF",
        "2100": "#A9CAFF",
        "2200": "#BFD7FF",
        "2300": "#D8E4F7",
        "2400": "#F0F2F5",
        "2500": "#FFFFFF"
      }
    }
  }
}
