{
  "slug": "switch",
  "runs": [
    {
      "savedAt": "2026-06-23T09:44:34.314Z",
      "report": {
        "ok": true,
        "slug": "switch",
        "message": "switch QA Playwright run OK — 2026-06-17T08:20:41.505Z",
        "suites": {
          "accessibility": {
            "suite": "accessibility",
            "passed": 39,
            "failed": 0,
            "skipped": 0,
            "logs": [
              "39 test(s) in Playwright report for accessibility.",
              "Axe: scan completed — 0 violation rules reported."
            ],
            "errors": [],
            "cases": [
              {
                "name": "[a11y] WCAG 2.1 AA axe scan — zero serious/critical + HTML report",
                "status": "passed",
                "durationMs": 5735
              },
              {
                "name": "[a11y] WCAG 2.1 AA axe scan — Default band",
                "status": "passed",
                "durationMs": 5106,
                "componentBand": "switch-figma-default"
              },
              {
                "name": "[a11y] WCAG 2.1 AA axe scan — size × selected band",
                "status": "passed",
                "durationMs": 5174,
                "componentBand": "switch-figma-size-selected"
              },
              {
                "name": "[a11y] WCAG 2.1 AA axe scan — Appearance band",
                "status": "passed",
                "durationMs": 5183,
                "componentBand": "switch-figma-appearance"
              },
              {
                "name": "[a11y] WCAG 2.1 AA axe scan — Accent band",
                "status": "passed",
                "durationMs": 5711,
                "componentBand": "switch-figma-accent"
              },
              {
                "name": "[a11y] WCAG 2.1 AA axe scan — Disabled band",
                "status": "passed",
                "durationMs": 4092,
                "componentBand": "switch-figma-disabled"
              },
              {
                "name": "[a11y] WCAG 2.1 AA axe scan — readOnly band",
                "status": "passed",
                "durationMs": 3981,
                "componentBand": "switch-figma-readonly"
              },
              {
                "name": "[a11y] WCAG 2.1 AA axe scan — selected (controlled) band",
                "status": "passed",
                "durationMs": 3875,
                "componentBand": "switch-figma-selected-interactive"
              },
              {
                "name": "[a11y] data-testid=\"sw-figma-default\" — zero serious/critical",
                "status": "passed",
                "durationMs": 4022
              },
              {
                "name": "[a11y] data-testid=\"sw-figma-size-m-selected-false\" — zero serious/critical",
                "status": "passed",
                "durationMs": 4008
              },
              {
                "name": "[a11y] data-testid=\"sw-figma-appearance-primary-on\" — zero serious/critical",
                "status": "passed",
                "durationMs": 3552
              },
              {
                "name": "[a11y] data-testid=\"sw-figma-accent-primary-on\" — zero serious/critical",
                "status": "passed",
                "durationMs": 3806
              },
              {
                "name": "[a11y] data-testid=\"sw-figma-disabled-true-on\" — zero serious/critical",
                "status": "passed",
                "durationMs": 5601
              },
              {
                "name": "[a11y] data-testid=\"sw-figma-readonly-true-on\" — zero serious/critical",
                "status": "passed",
                "durationMs": 3836
              },
              {
                "name": "[a11y] data-testid=\"sw-figma-selected-controlled\" — zero serious/critical",
                "status": "passed",
                "durationMs": 3878
              },
              {
                "name": "[a11y] Section 508 tag run — zero serious/critical",
                "status": "passed",
                "durationMs": 2533
              },
              {
                "name": "[a11y] axe label rule — showcase bands, zero serious/critical",
                "status": "passed",
                "durationMs": 2763
              },
              {
                "name": "[a11y] ARIA validity rules — zero serious/critical",
                "status": "passed",
                "durationMs": 3948
              },
              {
                "name": "[a11y] axe name rules — showcase bands, zero serious/critical",
                "status": "passed",
                "durationMs": 3356
              },
              {
                "name": "[a11y] page lang on <html>",
                "status": "passed",
                "durationMs": 2996
              },
              {
                "name": "[a11y] Viewport 320px — horizontal overflow check per showcase band",
                "status": "passed",
                "durationMs": 5783
              },
              {
                "name": "[a11y] 200% zoom — showcase switches remain visible",
                "status": "passed",
                "durationMs": 3157
              },
              {
                "name": "[a11y] Tab reaches a focusable control",
                "status": "passed",
                "durationMs": 3052
              },
              {
                "name": "[a11y] no keyboard trap (Tab cycle advances)",
                "status": "passed",
                "durationMs": 3611
              },
              {
                "name": "[a11y] focused element shows outline or box-shadow",
                "status": "passed",
                "durationMs": 3355
              },
              {
                "name": "[a11y] focus order — Tab visits multiple distinct targets",
                "status": "passed",
                "durationMs": 3175
              },
              {
                "name": "[a11y] Mode select activates with Enter when focused",
                "status": "passed",
                "durationMs": 3206
              },
              {
                "name": "[a11y] Mode select activates with Space when focused",
                "status": "passed",
                "durationMs": 3270
              },
              {
                "name": "[a11y] Switch QA page has no critical or serious axe violations",
                "status": "passed",
                "durationMs": 4580
              },
              {
                "name": "[a11y] section \"switch-figma-default\" has no critical or serious axe violations",
                "status": "passed",
                "durationMs": 3489,
                "componentBand": "switch-figma-default"
              },
              {
                "name": "[a11y] section \"switch-figma-size-selected\" has no critical or serious axe violations",
                "status": "passed",
                "durationMs": 4036,
                "componentBand": "switch-figma-size-selected"
              },
              {
                "name": "[a11y] section \"switch-figma-appearance\" has no critical or serious axe violations",
                "status": "passed",
                "durationMs": 3901,
                "componentBand": "switch-figma-appearance"
              },
              {
                "name": "[a11y] section \"switch-figma-accent\" has no critical or serious axe violations",
                "status": "passed",
                "durationMs": 3499,
                "componentBand": "switch-figma-accent"
              },
              {
                "name": "[a11y] section \"switch-figma-disabled\" has no critical or serious axe violations",
                "status": "passed",
                "durationMs": 3364,
                "componentBand": "switch-figma-disabled"
              },
              {
                "name": "[a11y] section \"switch-figma-readonly\" has no critical or serious axe violations",
                "status": "passed",
                "durationMs": 3410,
                "componentBand": "switch-figma-readonly"
              },
              {
                "name": "[a11y] section \"switch-figma-selected-interactive\" has no critical or serious axe violations",
                "status": "passed",
                "durationMs": 3325,
                "componentBand": "switch-figma-selected-interactive"
              },
              {
                "name": "[a11y] Default band switch has role switch and accessible name",
                "status": "passed",
                "durationMs": 2817
              },
              {
                "name": "[a11y] Disabled switch is not enabled",
                "status": "passed",
                "durationMs": 2784
              },
              {
                "name": "[a11y] Read-only switch exposes aria-readonly",
                "status": "passed",
                "durationMs": 2794
              }
            ],
            "axe": {
              "violations": []
            }
          },
          "functional": {
            "suite": "functional",
            "passed": 55,
            "failed": 0,
            "skipped": 0,
            "logs": [
              "55 test(s) in Playwright report for functional."
            ],
            "errors": [],
            "cases": [
              {
                "name": "[fn] 1.1 — no console errors on playground load",
                "status": "passed",
                "durationMs": 5719
              },
              {
                "name": "[fn] 1.2 — every playground data-testid is visible",
                "status": "passed",
                "durationMs": 10640
              },
              {
                "name": "[fn] 1.3 — every data-section is visible",
                "status": "passed",
                "durationMs": 3941
              },
              {
                "name": "[fn] 2.1 — size S/M/L wrappers expose data-size",
                "status": "passed",
                "durationMs": 3423
              },
              {
                "name": "[fn] 2.1 — appearance primary-off sets data-appearance on switch",
                "status": "passed",
                "durationMs": 3265
              },
              {
                "name": "[fn] 2.1 — selected-true cells are checked by default",
                "status": "passed",
                "durationMs": 2222
              },
              {
                "name": "[fn] 2.2 — Size scaling — S < M < L track width",
                "status": "passed",
                "durationMs": 1758
              },
              {
                "name": "[fn] 3.1 — click toggles aria-checked on default switch",
                "status": "passed",
                "durationMs": 3428
              },
              {
                "name": "[fn] 3.2 — disabled switch does not toggle on click",
                "status": "passed",
                "durationMs": 2603
              },
              {
                "name": "[fn] 3.3 — readOnly switch does not toggle on click",
                "status": "passed",
                "durationMs": 2706
              },
              {
                "name": "[fn] 3.4 — click outside removes focus from switch",
                "status": "passed",
                "durationMs": 3408
              },
              {
                "name": "[fn] 4.1 — Tab reaches default switch",
                "status": "passed",
                "durationMs": 3516
              },
              {
                "name": "[fn] 4.2 — Enter toggles focused default switch",
                "status": "passed",
                "durationMs": 3403
              },
              {
                "name": "[fn] 4.4 — Arrow keys (N/A)",
                "status": "passed",
                "durationMs": 7728
              },
              {
                "name": "[fn] 4.5 — Home and End (N/A)",
                "status": "passed",
                "durationMs": 3058
              },
              {
                "name": "[fn] 4.6 — Escape (N/A)",
                "status": "passed",
                "durationMs": 3159
              },
              {
                "name": "[fn] 4.7 — Tab through page without keyboard trap",
                "status": "passed",
                "durationMs": 2938
              },
              {
                "name": "[fn] 5.1 — click focuses default switch",
                "status": "passed",
                "durationMs": 3361
              },
              {
                "name": "[fn] 5.2 — focus ring visible on default switch",
                "status": "passed",
                "durationMs": 6855
              },
              {
                "name": "[fn] 5.5 — autoFocus (N/A)",
                "status": "passed",
                "durationMs": 2975
              },
              {
                "name": "[fn] 6.1 — default switch starts unchecked",
                "status": "passed",
                "durationMs": 3009
              },
              {
                "name": "[fn] 6.2 — appearance-on cells render checked",
                "status": "passed",
                "durationMs": 3172
              },
              {
                "name": "[fn] 6.3 — disabled switch is not enabled",
                "status": "passed",
                "durationMs": 3368
              },
              {
                "name": "[fn] 6.4 — readOnly switch exposes aria-readonly",
                "status": "passed",
                "durationMs": 8151
              },
              {
                "name": "[fn] 6.5 — Error state (N/A)",
                "status": "passed",
                "durationMs": 3642
              },
              {
                "name": "[fn] 6.6 — Loading state (N/A)",
                "status": "passed",
                "durationMs": 2978
              },
              {
                "name": "[fn] 7.1 — start/end slots (N/A)",
                "status": "passed",
                "durationMs": 2948
              },
              {
                "name": "[fn] 8.1 — click toggles off → on → off with aria-checked",
                "status": "passed",
                "durationMs": 2780
              },
              {
                "name": "[fn] 8.2 — Single select (N/A)",
                "status": "passed",
                "durationMs": 1571
              },
              {
                "name": "[fn] 8.3 — Indeterminate (N/A)",
                "status": "passed",
                "durationMs": 3351
              },
              {
                "name": "[fn] 9.1 — Typing (N/A)",
                "status": "passed",
                "durationMs": 2197
              },
              {
                "name": "[fn] 10.1 — accent prop renders accent on/off pair",
                "status": "passed",
                "durationMs": 2798
              },
              {
                "name": "[fn] 11.3 — Progress value (N/A)",
                "status": "passed",
                "durationMs": 3244
              },
              {
                "name": "[fn] 12.1 — fullWidth (N/A)",
                "status": "passed",
                "durationMs": 3067
              },
              {
                "name": "[fn] 12.2 — visible at 320px viewport",
                "status": "passed",
                "durationMs": 8833
              },
              {
                "name": "[fn] 12.2 — visible at 1440px viewport",
                "status": "passed",
                "durationMs": 7666
              },
              {
                "name": "[fn] 12.3 — size band rows layout horizontally",
                "status": "passed",
                "durationMs": 3311
              },
              {
                "name": "[fn] Smoke — Page heading reads “Switch”",
                "status": "passed",
                "durationMs": 3383
              },
              {
                "name": "[fn] Smoke — Default switch is visible",
                "status": "passed",
                "durationMs": 2286
              },
              {
                "name": "[fn] Smoke — Appearance primary-off switch is visible",
                "status": "passed",
                "durationMs": 1771
              },
              {
                "name": "[fn] shows Switch page heading",
                "status": "passed",
                "durationMs": 2725
              },
              {
                "name": "[fn] theme toggle updates label",
                "status": "passed",
                "durationMs": 3452
              },
              {
                "name": "[fn] scenario and report tabs are present",
                "status": "passed",
                "durationMs": 2616
              },
              {
                "name": "[fn] figma validation tab mounts grid",
                "status": "passed",
                "durationMs": 3487
              },
              {
                "name": "[fn] renders switch: sw-figma-default",
                "status": "passed",
                "durationMs": 2902
              },
              {
                "name": "[fn] renders switch: sw-figma-size-s-selected-false",
                "status": "passed",
                "durationMs": 3264
              },
              {
                "name": "[fn] renders switch: sw-figma-size-s-selected-true",
                "status": "passed",
                "durationMs": 5351
              },
              {
                "name": "[fn] renders switch: sw-figma-appearance-primary-off",
                "status": "passed",
                "durationMs": 5310
              },
              {
                "name": "[fn] renders switch: sw-figma-accent-primary-off",
                "status": "passed",
                "durationMs": 4109
              },
              {
                "name": "[fn] renders switch: sw-figma-disabled-false",
                "status": "passed",
                "durationMs": 3315
              },
              {
                "name": "[fn] renders switch: sw-figma-readonly-true-off",
                "status": "passed",
                "durationMs": 3160
              },
              {
                "name": "[fn] renders switch: sw-figma-selected-controlled",
                "status": "passed",
                "durationMs": 2908
              },
              {
                "name": "[fn] default switch toggles on click",
                "status": "passed",
                "durationMs": 2997
              },
              {
                "name": "[fn] controlled switch toggles via click",
                "status": "passed",
                "durationMs": 2928
              },
              {
                "name": "[fn] Space toggles focused default switch",
                "status": "passed",
                "durationMs": 3520
              }
            ]
          },
          "performance": {
            "suite": "performance",
            "passed": 0,
            "failed": 0,
            "skipped": 0,
            "logs": [
              "Performance suite is not executed in apps/qa-playground switch Playwright bundle."
            ],
            "errors": []
          }
        }
      }
    },
    {
      "savedAt": "2026-06-17T08:20:41.508Z",
      "report": {
        "ok": true,
        "slug": "switch",
        "message": "switch QA Playwright run OK — 2026-06-04T10:14:45.479Z",
        "suites": {
          "accessibility": {
            "suite": "accessibility",
            "passed": 39,
            "failed": 0,
            "skipped": 0,
            "logs": [
              "39 test(s) in Playwright report for accessibility.",
              "Axe: 1 violation rule(s) reported."
            ],
            "errors": [],
            "cases": [
              {
                "name": "[a11y] WCAG 2.1 AA axe scan — zero serious/critical + HTML report",
                "status": "passed",
                "durationMs": 4263
              },
              {
                "name": "[a11y] WCAG 2.1 AA axe scan — Default band",
                "status": "passed",
                "durationMs": 3746,
                "componentBand": "switch-figma-default"
              },
              {
                "name": "[a11y] WCAG 2.1 AA axe scan — size × selected band",
                "status": "passed",
                "durationMs": 3769,
                "componentBand": "switch-figma-size-selected"
              },
              {
                "name": "[a11y] WCAG 2.1 AA axe scan — Appearance band",
                "status": "passed",
                "durationMs": 3823,
                "componentBand": "switch-figma-appearance"
              },
              {
                "name": "[a11y] WCAG 2.1 AA axe scan — Accent band",
                "status": "passed",
                "durationMs": 4490,
                "componentBand": "switch-figma-accent"
              },
              {
                "name": "[a11y] WCAG 2.1 AA axe scan — Disabled band",
                "status": "passed",
                "durationMs": 3349,
                "componentBand": "switch-figma-disabled"
              },
              {
                "name": "[a11y] WCAG 2.1 AA axe scan — readOnly band",
                "status": "passed",
                "durationMs": 3709,
                "componentBand": "switch-figma-readonly"
              },
              {
                "name": "[a11y] WCAG 2.1 AA axe scan — selected (controlled) band",
                "status": "passed",
                "durationMs": 3596,
                "componentBand": "switch-figma-selected-interactive"
              },
              {
                "name": "[a11y] data-testid=\"sw-figma-default\" — zero serious/critical",
                "status": "passed",
                "durationMs": 3467
              },
              {
                "name": "[a11y] data-testid=\"sw-figma-size-m-selected-false\" — zero serious/critical",
                "status": "passed",
                "durationMs": 3538
              },
              {
                "name": "[a11y] data-testid=\"sw-figma-appearance-primary-on\" — zero serious/critical",
                "status": "passed",
                "durationMs": 2918
              },
              {
                "name": "[a11y] data-testid=\"sw-figma-accent-primary-on\" — zero serious/critical",
                "status": "passed",
                "durationMs": 3084
              },
              {
                "name": "[a11y] data-testid=\"sw-figma-disabled-true-on\" — zero serious/critical",
                "status": "passed",
                "durationMs": 3063
              },
              {
                "name": "[a11y] data-testid=\"sw-figma-readonly-true-on\" — zero serious/critical",
                "status": "passed",
                "durationMs": 3109
              },
              {
                "name": "[a11y] data-testid=\"sw-figma-selected-controlled\" — zero serious/critical",
                "status": "passed",
                "durationMs": 2978
              },
              {
                "name": "[a11y] Section 508 tag run — zero serious/critical",
                "status": "passed",
                "durationMs": 2137
              },
              {
                "name": "[a11y] axe label rule — showcase bands, zero serious/critical",
                "status": "passed",
                "durationMs": 2829
              },
              {
                "name": "[a11y] ARIA validity rules — zero serious/critical",
                "status": "passed",
                "durationMs": 3251
              },
              {
                "name": "[a11y] axe name rules — showcase bands, zero serious/critical",
                "status": "passed",
                "durationMs": 3438
              },
              {
                "name": "[a11y] page lang on <html>",
                "status": "passed",
                "durationMs": 2770
              },
              {
                "name": "[a11y] Viewport 320px — horizontal overflow check per showcase band",
                "status": "passed",
                "durationMs": 4475
              },
              {
                "name": "[a11y] 200% zoom — showcase switches remain visible",
                "status": "passed",
                "durationMs": 2815
              },
              {
                "name": "[a11y] Tab reaches a focusable control",
                "status": "passed",
                "durationMs": 2730
              },
              {
                "name": "[a11y] no keyboard trap (Tab cycle advances)",
                "status": "passed",
                "durationMs": 3041
              },
              {
                "name": "[a11y] focused element shows outline or box-shadow",
                "status": "passed",
                "durationMs": 2643
              },
              {
                "name": "[a11y] focus order — Tab visits multiple distinct targets",
                "status": "passed",
                "durationMs": 2525
              },
              {
                "name": "[a11y] Mode select activates with Enter when focused",
                "status": "passed",
                "durationMs": 3020
              },
              {
                "name": "[a11y] Mode select activates with Space when focused",
                "status": "passed",
                "durationMs": 3088
              },
              {
                "name": "[a11y] Switch QA page has no critical or serious axe violations",
                "status": "passed",
                "durationMs": 3633
              },
              {
                "name": "[a11y] section \"switch-figma-default\" has no critical or serious axe violations",
                "status": "passed",
                "durationMs": 3182,
                "componentBand": "switch-figma-default"
              },
              {
                "name": "[a11y] section \"switch-figma-size-selected\" has no critical or serious axe violations",
                "status": "passed",
                "durationMs": 2748,
                "componentBand": "switch-figma-size-selected"
              },
              {
                "name": "[a11y] section \"switch-figma-appearance\" has no critical or serious axe violations",
                "status": "passed",
                "durationMs": 3193,
                "componentBand": "switch-figma-appearance"
              },
              {
                "name": "[a11y] section \"switch-figma-accent\" has no critical or serious axe violations",
                "status": "passed",
                "durationMs": 3126,
                "componentBand": "switch-figma-accent"
              },
              {
                "name": "[a11y] section \"switch-figma-disabled\" has no critical or serious axe violations",
                "status": "passed",
                "durationMs": 2995,
                "componentBand": "switch-figma-disabled"
              },
              {
                "name": "[a11y] section \"switch-figma-readonly\" has no critical or serious axe violations",
                "status": "passed",
                "durationMs": 3110,
                "componentBand": "switch-figma-readonly"
              },
              {
                "name": "[a11y] section \"switch-figma-selected-interactive\" has no critical or serious axe violations",
                "status": "passed",
                "durationMs": 2428,
                "componentBand": "switch-figma-selected-interactive"
              },
              {
                "name": "[a11y] Default band switch has role switch and accessible name",
                "status": "passed",
                "durationMs": 2156
              },
              {
                "name": "[a11y] Disabled switch is not enabled",
                "status": "passed",
                "durationMs": 2477
              },
              {
                "name": "[a11y] Read-only switch exposes aria-readonly",
                "status": "passed",
                "durationMs": 2505
              }
            ],
            "axe": {
              "violations": [
                {
                  "id": "color-contrast",
                  "impact": "serious",
                  "description": "Ensure the contrast between foreground and background colors meets WCAG 2 AA minimum contrast ratio thresholds",
                  "helpUrl": "https://dequeuniversity.com/rules/axe/4.11/color-contrast?application=playwright",
                  "nodes": 2
                }
              ]
            }
          },
          "functional": {
            "suite": "functional",
            "passed": 55,
            "failed": 0,
            "skipped": 0,
            "logs": [
              "55 test(s) in Playwright report for functional."
            ],
            "errors": [],
            "cases": [
              {
                "name": "[fn] 1.1 — no console errors on playground load",
                "status": "passed",
                "durationMs": 5093
              },
              {
                "name": "[fn] 1.2 — every playground data-testid is visible",
                "status": "passed",
                "durationMs": 5253
              },
              {
                "name": "[fn] 1.3 — every data-section is visible",
                "status": "passed",
                "durationMs": 2873
              },
              {
                "name": "[fn] 2.1 — size S/M/L wrappers expose data-size",
                "status": "passed",
                "durationMs": 2793
              },
              {
                "name": "[fn] 2.1 — appearance primary-off sets data-appearance on switch",
                "status": "passed",
                "durationMs": 2630
              },
              {
                "name": "[fn] 2.1 — selected-true cells are checked by default",
                "status": "passed",
                "durationMs": 2238
              },
              {
                "name": "[fn] 2.2 — Size scaling — S < M < L track width",
                "status": "passed",
                "durationMs": 1068
              },
              {
                "name": "[fn] 3.1 — click toggles aria-checked on default switch",
                "status": "passed",
                "durationMs": 2592
              },
              {
                "name": "[fn] 3.2 — disabled switch does not toggle on click",
                "status": "passed",
                "durationMs": 3888
              },
              {
                "name": "[fn] 3.3 — readOnly switch does not toggle on click",
                "status": "passed",
                "durationMs": 4586
              },
              {
                "name": "[fn] 3.4 — click outside removes focus from switch",
                "status": "passed",
                "durationMs": 3767
              },
              {
                "name": "[fn] 4.1 — Tab reaches default switch",
                "status": "passed",
                "durationMs": 3314
              },
              {
                "name": "[fn] 4.2 — Enter toggles focused default switch",
                "status": "passed",
                "durationMs": 3037
              },
              {
                "name": "[fn] 4.4 — Arrow keys (N/A)",
                "status": "passed",
                "durationMs": 2870
              },
              {
                "name": "[fn] 4.5 — Home and End (N/A)",
                "status": "passed",
                "durationMs": 2774
              },
              {
                "name": "[fn] 4.6 — Escape (N/A)",
                "status": "passed",
                "durationMs": 2794
              },
              {
                "name": "[fn] 4.7 — Tab through page without keyboard trap",
                "status": "passed",
                "durationMs": 2933
              },
              {
                "name": "[fn] 5.1 — click focuses default switch",
                "status": "passed",
                "durationMs": 2610
              },
              {
                "name": "[fn] 5.2 — focus ring visible on default switch",
                "status": "passed",
                "durationMs": 2981
              },
              {
                "name": "[fn] 5.5 — autoFocus (N/A)",
                "status": "passed",
                "durationMs": 3302
              },
              {
                "name": "[fn] 6.1 — default switch starts unchecked",
                "status": "passed",
                "durationMs": 4292
              },
              {
                "name": "[fn] 6.2 — appearance-on cells render checked",
                "status": "passed",
                "durationMs": 3783
              },
              {
                "name": "[fn] 6.3 — disabled switch is not enabled",
                "status": "passed",
                "durationMs": 3332
              },
              {
                "name": "[fn] 6.4 — readOnly switch exposes aria-readonly",
                "status": "passed",
                "durationMs": 2815
              },
              {
                "name": "[fn] 6.5 — Error state (N/A)",
                "status": "passed",
                "durationMs": 2991
              },
              {
                "name": "[fn] 6.6 — Loading state (N/A)",
                "status": "passed",
                "durationMs": 2625
              },
              {
                "name": "[fn] 7.1 — start/end slots (N/A)",
                "status": "passed",
                "durationMs": 2736
              },
              {
                "name": "[fn] 8.1 — click toggles off → on → off with aria-checked",
                "status": "passed",
                "durationMs": 3142
              },
              {
                "name": "[fn] 8.2 — Single select (N/A)",
                "status": "passed",
                "durationMs": 2435
              },
              {
                "name": "[fn] 8.3 — Indeterminate (N/A)",
                "status": "passed",
                "durationMs": 3554
              },
              {
                "name": "[fn] 9.1 — Typing (N/A)",
                "status": "passed",
                "durationMs": 3473
              },
              {
                "name": "[fn] 10.1 — accent prop renders accent on/off pair",
                "status": "passed",
                "durationMs": 4414
              },
              {
                "name": "[fn] 11.3 — Progress value (N/A)",
                "status": "passed",
                "durationMs": 3323
              },
              {
                "name": "[fn] 12.1 — fullWidth (N/A)",
                "status": "passed",
                "durationMs": 3337
              },
              {
                "name": "[fn] 12.2 — visible at 320px viewport",
                "status": "passed",
                "durationMs": 5308
              },
              {
                "name": "[fn] 12.2 — visible at 1440px viewport",
                "status": "passed",
                "durationMs": 4939
              },
              {
                "name": "[fn] 12.3 — size band rows layout horizontally",
                "status": "passed",
                "durationMs": 2806
              },
              {
                "name": "[fn] Smoke — Page heading reads “Switch”",
                "status": "passed",
                "durationMs": 2681
              },
              {
                "name": "[fn] Smoke — Default switch is visible",
                "status": "passed",
                "durationMs": 1398
              },
              {
                "name": "[fn] Smoke — Appearance primary-off switch is visible",
                "status": "passed",
                "durationMs": 997
              },
              {
                "name": "[fn] shows Switch page heading",
                "status": "passed",
                "durationMs": 2580
              },
              {
                "name": "[fn] theme toggle updates label",
                "status": "passed",
                "durationMs": 4232
              },
              {
                "name": "[fn] scenario and report tabs are present",
                "status": "passed",
                "durationMs": 4258
              },
              {
                "name": "[fn] figma validation tab mounts grid",
                "status": "passed",
                "durationMs": 3646
              },
              {
                "name": "[fn] renders switch: sw-figma-default",
                "status": "passed",
                "durationMs": 2858
              },
              {
                "name": "[fn] renders switch: sw-figma-size-s-selected-false",
                "status": "passed",
                "durationMs": 3200
              },
              {
                "name": "[fn] renders switch: sw-figma-size-s-selected-true",
                "status": "passed",
                "durationMs": 3226
              },
              {
                "name": "[fn] renders switch: sw-figma-appearance-primary-off",
                "status": "passed",
                "durationMs": 2284
              },
              {
                "name": "[fn] renders switch: sw-figma-accent-primary-off",
                "status": "passed",
                "durationMs": 2934
              },
              {
                "name": "[fn] renders switch: sw-figma-disabled-false",
                "status": "passed",
                "durationMs": 2703
              },
              {
                "name": "[fn] renders switch: sw-figma-readonly-true-off",
                "status": "passed",
                "durationMs": 2572
              },
              {
                "name": "[fn] renders switch: sw-figma-selected-controlled",
                "status": "passed",
                "durationMs": 2387
              },
              {
                "name": "[fn] default switch toggles on click",
                "status": "passed",
                "durationMs": 4114
              },
              {
                "name": "[fn] controlled switch toggles via click",
                "status": "passed",
                "durationMs": 4230
              },
              {
                "name": "[fn] Space toggles focused default switch",
                "status": "passed",
                "durationMs": 4802
              }
            ]
          },
          "performance": {
            "suite": "performance",
            "passed": 0,
            "failed": 0,
            "skipped": 0,
            "logs": [
              "Performance suite is not executed in apps/qa-playground switch Playwright bundle."
            ],
            "errors": []
          }
        }
      }
    },
    {
      "savedAt": "2026-06-04T10:14:45.480Z",
      "report": {
        "ok": false,
        "slug": "switch",
        "message": "switch QA Playwright run had failures — 2026-06-04T09:03:26.688Z",
        "suites": {
          "accessibility": {
            "suite": "accessibility",
            "passed": 37,
            "failed": 2,
            "skipped": 0,
            "logs": [
              "39 test(s) in Playwright report for accessibility.",
              "Axe: 1 violation rule(s) reported."
            ],
            "errors": [
              "[a11y] Mode select activates with Enter when focused: Test timeout of 30000ms exceeded.",
              "[a11y] Mode select activates with Space when focused: Test timeout of 30000ms exceeded."
            ],
            "cases": [
              {
                "name": "[a11y] WCAG 2.1 AA axe scan — zero serious/critical + HTML report",
                "status": "passed",
                "durationMs": 8045
              },
              {
                "name": "[a11y] WCAG 2.1 AA axe scan — Default band",
                "status": "passed",
                "durationMs": 12854,
                "componentBand": "switch-figma-default"
              },
              {
                "name": "[a11y] WCAG 2.1 AA axe scan — size × selected band",
                "status": "passed",
                "durationMs": 7088,
                "componentBand": "switch-figma-size-selected"
              },
              {
                "name": "[a11y] WCAG 2.1 AA axe scan — Appearance band",
                "status": "passed",
                "durationMs": 6906,
                "componentBand": "switch-figma-appearance"
              },
              {
                "name": "[a11y] WCAG 2.1 AA axe scan — Accent band",
                "status": "passed",
                "durationMs": 12761,
                "componentBand": "switch-figma-accent"
              },
              {
                "name": "[a11y] WCAG 2.1 AA axe scan — Disabled band",
                "status": "passed",
                "durationMs": 3355,
                "componentBand": "switch-figma-disabled"
              },
              {
                "name": "[a11y] WCAG 2.1 AA axe scan — readOnly band",
                "status": "passed",
                "durationMs": 4079,
                "componentBand": "switch-figma-readonly"
              },
              {
                "name": "[a11y] WCAG 2.1 AA axe scan — selected (controlled) band",
                "status": "passed",
                "durationMs": 3363,
                "componentBand": "switch-figma-selected-interactive"
              },
              {
                "name": "[a11y] data-testid=\"sw-figma-default\" — zero serious/critical",
                "status": "passed",
                "durationMs": 3014
              },
              {
                "name": "[a11y] data-testid=\"sw-figma-size-m-selected-false\" — zero serious/critical",
                "status": "passed",
                "durationMs": 2728
              },
              {
                "name": "[a11y] data-testid=\"sw-figma-appearance-primary-on\" — zero serious/critical",
                "status": "passed",
                "durationMs": 2571
              },
              {
                "name": "[a11y] data-testid=\"sw-figma-accent-primary-on\" — zero serious/critical",
                "status": "passed",
                "durationMs": 4110
              },
              {
                "name": "[a11y] data-testid=\"sw-figma-disabled-true-on\" — zero serious/critical",
                "status": "passed",
                "durationMs": 3792
              },
              {
                "name": "[a11y] data-testid=\"sw-figma-readonly-true-on\" — zero serious/critical",
                "status": "passed",
                "durationMs": 4361
              },
              {
                "name": "[a11y] data-testid=\"sw-figma-selected-controlled\" — zero serious/critical",
                "status": "passed",
                "durationMs": 4410
              },
              {
                "name": "[a11y] Section 508 tag run — zero serious/critical",
                "status": "passed",
                "durationMs": 4125
              },
              {
                "name": "[a11y] axe label rule — showcase bands, zero serious/critical",
                "status": "passed",
                "durationMs": 3068
              },
              {
                "name": "[a11y] ARIA validity rules — zero serious/critical",
                "status": "passed",
                "durationMs": 3431
              },
              {
                "name": "[a11y] axe name rules — showcase bands, zero serious/critical",
                "status": "passed",
                "durationMs": 3577
              },
              {
                "name": "[a11y] page lang on <html>",
                "status": "passed",
                "durationMs": 3112
              },
              {
                "name": "[a11y] Viewport 320px — horizontal overflow check per showcase band",
                "status": "passed",
                "durationMs": 6202
              },
              {
                "name": "[a11y] 200% zoom — showcase switches remain visible",
                "status": "passed",
                "durationMs": 3877
              },
              {
                "name": "[a11y] Tab reaches a focusable control",
                "status": "passed",
                "durationMs": 3573
              },
              {
                "name": "[a11y] no keyboard trap (Tab cycle advances)",
                "status": "passed",
                "durationMs": 3644
              },
              {
                "name": "[a11y] focused element shows outline or box-shadow",
                "status": "passed",
                "durationMs": 3370
              },
              {
                "name": "[a11y] focus order — Tab visits multiple distinct targets",
                "status": "passed",
                "durationMs": 3221
              },
              {
                "name": "[a11y] Mode select activates with Enter when focused",
                "status": "failed",
                "durationMs": 30131,
                "error": "Test timeout of 30000ms exceeded."
              },
              {
                "name": "[a11y] Mode select activates with Space when focused",
                "status": "failed",
                "durationMs": 30108,
                "error": "Test timeout of 30000ms exceeded."
              },
              {
                "name": "[a11y] Switch QA page has no critical or serious axe violations",
                "status": "passed",
                "durationMs": 3956
              },
              {
                "name": "[a11y] section \"switch-figma-default\" has no critical or serious axe violations",
                "status": "passed",
                "durationMs": 3317,
                "componentBand": "switch-figma-default"
              },
              {
                "name": "[a11y] section \"switch-figma-size-selected\" has no critical or serious axe violations",
                "status": "passed",
                "durationMs": 2391,
                "componentBand": "switch-figma-size-selected"
              },
              {
                "name": "[a11y] section \"switch-figma-appearance\" has no critical or serious axe violations",
                "status": "passed",
                "durationMs": 1993,
                "componentBand": "switch-figma-appearance"
              },
              {
                "name": "[a11y] section \"switch-figma-accent\" has no critical or serious axe violations",
                "status": "passed",
                "durationMs": 2062,
                "componentBand": "switch-figma-accent"
              },
              {
                "name": "[a11y] section \"switch-figma-disabled\" has no critical or serious axe violations",
                "status": "passed",
                "durationMs": 1934,
                "componentBand": "switch-figma-disabled"
              },
              {
                "name": "[a11y] section \"switch-figma-readonly\" has no critical or serious axe violations",
                "status": "passed",
                "durationMs": 1955,
                "componentBand": "switch-figma-readonly"
              },
              {
                "name": "[a11y] section \"switch-figma-selected-interactive\" has no critical or serious axe violations",
                "status": "passed",
                "durationMs": 1894,
                "componentBand": "switch-figma-selected-interactive"
              },
              {
                "name": "[a11y] Default band switch has role switch and accessible name",
                "status": "passed",
                "durationMs": 1332
              },
              {
                "name": "[a11y] Disabled switch is not enabled",
                "status": "passed",
                "durationMs": 1461
              },
              {
                "name": "[a11y] Read-only switch exposes aria-readonly",
                "status": "passed",
                "durationMs": 1722
              }
            ],
            "axe": {
              "violations": [
                {
                  "id": "color-contrast",
                  "impact": "serious",
                  "description": "Ensure the contrast between foreground and background colors meets WCAG 2 AA minimum contrast ratio thresholds",
                  "helpUrl": "https://dequeuniversity.com/rules/axe/4.11/color-contrast?application=playwright",
                  "nodes": 2
                }
              ]
            }
          },
          "functional": {
            "suite": "functional",
            "passed": 55,
            "failed": 0,
            "skipped": 0,
            "logs": [
              "55 test(s) in Playwright report for functional."
            ],
            "errors": [],
            "cases": [
              {
                "name": "[fn] 1.1 — no console errors on playground load",
                "status": "passed",
                "durationMs": 2738
              },
              {
                "name": "[fn] 1.2 — every playground data-testid is visible",
                "status": "passed",
                "durationMs": 6131
              },
              {
                "name": "[fn] 1.3 — every data-section is visible",
                "status": "passed",
                "durationMs": 1753
              },
              {
                "name": "[fn] 2.1 — size S/M/L wrappers expose data-size",
                "status": "passed",
                "durationMs": 1591
              },
              {
                "name": "[fn] 2.1 — appearance primary-off sets data-appearance on switch",
                "status": "passed",
                "durationMs": 1621
              },
              {
                "name": "[fn] 2.1 — selected-true cells are checked by default",
                "status": "passed",
                "durationMs": 1849
              },
              {
                "name": "[fn] 2.2 — Size scaling — S < M < L track width",
                "status": "passed",
                "durationMs": 1836
              },
              {
                "name": "[fn] 3.1 — click toggles aria-checked on default switch",
                "status": "passed",
                "durationMs": 1841
              },
              {
                "name": "[fn] 3.2 — disabled switch does not toggle on click",
                "status": "passed",
                "durationMs": 2331
              },
              {
                "name": "[fn] 3.3 — readOnly switch does not toggle on click",
                "status": "passed",
                "durationMs": 1735
              },
              {
                "name": "[fn] 3.4 — click outside removes focus from switch",
                "status": "passed",
                "durationMs": 1380
              },
              {
                "name": "[fn] 4.1 — Tab reaches default switch",
                "status": "passed",
                "durationMs": 2169
              },
              {
                "name": "[fn] 4.2 — Enter toggles focused default switch",
                "status": "passed",
                "durationMs": 2364
              },
              {
                "name": "[fn] 4.4 — Arrow keys (N/A)",
                "status": "passed",
                "durationMs": 1917
              },
              {
                "name": "[fn] 4.5 — Home and End (N/A)",
                "status": "passed",
                "durationMs": 1744
              },
              {
                "name": "[fn] 4.6 — Escape (N/A)",
                "status": "passed",
                "durationMs": 1910
              },
              {
                "name": "[fn] 4.7 — Tab through page without keyboard trap",
                "status": "passed",
                "durationMs": 1792
              },
              {
                "name": "[fn] 5.1 — click focuses default switch",
                "status": "passed",
                "durationMs": 1811
              },
              {
                "name": "[fn] 5.2 — focus ring visible on default switch",
                "status": "passed",
                "durationMs": 1893
              },
              {
                "name": "[fn] 5.5 — autoFocus (N/A)",
                "status": "passed",
                "durationMs": 1484
              },
              {
                "name": "[fn] 6.1 — default switch starts unchecked",
                "status": "passed",
                "durationMs": 1342
              },
              {
                "name": "[fn] 6.2 — appearance-on cells render checked",
                "status": "passed",
                "durationMs": 1350
              },
              {
                "name": "[fn] 6.3 — disabled switch is not enabled",
                "status": "passed",
                "durationMs": 1586
              },
              {
                "name": "[fn] 6.4 — readOnly switch exposes aria-readonly",
                "status": "passed",
                "durationMs": 1415
              },
              {
                "name": "[fn] 6.5 — Error state (N/A)",
                "status": "passed",
                "durationMs": 1170
              },
              {
                "name": "[fn] 6.6 — Loading state (N/A)",
                "status": "passed",
                "durationMs": 1150
              },
              {
                "name": "[fn] 7.1 — start/end slots (N/A)",
                "status": "passed",
                "durationMs": 1266
              },
              {
                "name": "[fn] 8.1 — click toggles off → on → off with aria-checked",
                "status": "passed",
                "durationMs": 1362
              },
              {
                "name": "[fn] 8.2 — Single select (N/A)",
                "status": "passed",
                "durationMs": 1210
              },
              {
                "name": "[fn] 8.3 — Indeterminate (N/A)",
                "status": "passed",
                "durationMs": 1850
              },
              {
                "name": "[fn] 9.1 — Typing (N/A)",
                "status": "passed",
                "durationMs": 1514
              },
              {
                "name": "[fn] 10.1 — accent prop renders accent on/off pair",
                "status": "passed",
                "durationMs": 1410
              },
              {
                "name": "[fn] 11.3 — Progress value (N/A)",
                "status": "passed",
                "durationMs": 1272
              },
              {
                "name": "[fn] 12.1 — fullWidth (N/A)",
                "status": "passed",
                "durationMs": 1542
              },
              {
                "name": "[fn] 12.2 — visible at 320px viewport",
                "status": "passed",
                "durationMs": 2181
              },
              {
                "name": "[fn] 12.2 — visible at 1440px viewport",
                "status": "passed",
                "durationMs": 1860
              },
              {
                "name": "[fn] 12.3 — size band rows layout horizontally",
                "status": "passed",
                "durationMs": 1409
              },
              {
                "name": "[fn] Smoke — Page heading reads “Switch”",
                "status": "passed",
                "durationMs": 1310
              },
              {
                "name": "[fn] Smoke — Default switch is visible",
                "status": "passed",
                "durationMs": 1187
              },
              {
                "name": "[fn] Smoke — Appearance primary-off switch is visible",
                "status": "passed",
                "durationMs": 989
              },
              {
                "name": "[fn] shows Switch page heading",
                "status": "passed",
                "durationMs": 1672
              },
              {
                "name": "[fn] theme toggle updates label",
                "status": "passed",
                "durationMs": 2511
              },
              {
                "name": "[fn] scenario and report tabs are present",
                "status": "passed",
                "durationMs": 1973
              },
              {
                "name": "[fn] figma validation tab mounts grid",
                "status": "passed",
                "durationMs": 2737
              },
              {
                "name": "[fn] renders switch: sw-figma-default",
                "status": "passed",
                "durationMs": 2042
              },
              {
                "name": "[fn] renders switch: sw-figma-size-s-selected-false",
                "status": "passed",
                "durationMs": 1935
              },
              {
                "name": "[fn] renders switch: sw-figma-size-s-selected-true",
                "status": "passed",
                "durationMs": 2347
              },
              {
                "name": "[fn] renders switch: sw-figma-appearance-primary-off",
                "status": "passed",
                "durationMs": 1978
              },
              {
                "name": "[fn] renders switch: sw-figma-accent-primary-off",
                "status": "passed",
                "durationMs": 1894
              },
              {
                "name": "[fn] renders switch: sw-figma-disabled-false",
                "status": "passed",
                "durationMs": 1724
              },
              {
                "name": "[fn] renders switch: sw-figma-readonly-true-off",
                "status": "passed",
                "durationMs": 1824
              },
              {
                "name": "[fn] renders switch: sw-figma-selected-controlled",
                "status": "passed",
                "durationMs": 1372
              },
              {
                "name": "[fn] default switch toggles on click",
                "status": "passed",
                "durationMs": 2195
              },
              {
                "name": "[fn] controlled switch toggles via click",
                "status": "passed",
                "durationMs": 2248
              },
              {
                "name": "[fn] Space toggles focused default switch",
                "status": "passed",
                "durationMs": 1627
              }
            ]
          },
          "performance": {
            "suite": "performance",
            "passed": 0,
            "failed": 0,
            "skipped": 0,
            "logs": [
              "Performance suite is not executed in apps/qa-playground switch Playwright bundle."
            ],
            "errors": []
          }
        }
      }
    },
    {
      "savedAt": "2026-06-04T09:03:26.689Z",
      "report": {
        "ok": false,
        "slug": "switch",
        "message": "switch QA Playwright run had failures — 2026-05-29T13:08:34.115Z",
        "suites": {
          "accessibility": {
            "suite": "accessibility",
            "passed": 38,
            "failed": 1,
            "skipped": 0,
            "logs": [
              "39 test(s) in Playwright report for accessibility.",
              "Axe: 2 violation rule(s) reported."
            ],
            "errors": [
              "[a11y] Switch QA page has no critical or serious axe violations: An icon is exposed as an image (role=\"img\") without a name. Decorative icons should be aria-hidden; meaningful icons need aria-label."
            ],
            "cases": [
              {
                "name": "[a11y] WCAG 2.1 AA axe scan — zero serious/critical + HTML report",
                "status": "passed",
                "durationMs": 4321
              },
              {
                "name": "[a11y] WCAG 2.1 AA axe scan — Default band",
                "status": "passed",
                "durationMs": 4267,
                "componentBand": "switch-figma-default"
              },
              {
                "name": "[a11y] WCAG 2.1 AA axe scan — size × selected band",
                "status": "passed",
                "durationMs": 3819,
                "componentBand": "switch-figma-size-selected"
              },
              {
                "name": "[a11y] WCAG 2.1 AA axe scan — Appearance band",
                "status": "passed",
                "durationMs": 4047,
                "componentBand": "switch-figma-appearance"
              },
              {
                "name": "[a11y] WCAG 2.1 AA axe scan — Accent band",
                "status": "passed",
                "durationMs": 3940,
                "componentBand": "switch-figma-accent"
              },
              {
                "name": "[a11y] WCAG 2.1 AA axe scan — Disabled band",
                "status": "passed",
                "durationMs": 2614,
                "componentBand": "switch-figma-disabled"
              },
              {
                "name": "[a11y] WCAG 2.1 AA axe scan — readOnly band",
                "status": "passed",
                "durationMs": 3456,
                "componentBand": "switch-figma-readonly"
              },
              {
                "name": "[a11y] WCAG 2.1 AA axe scan — selected (controlled) band",
                "status": "passed",
                "durationMs": 3384,
                "componentBand": "switch-figma-selected-interactive"
              },
              {
                "name": "[a11y] data-testid=\"sw-figma-default\" — zero serious/critical",
                "status": "passed",
                "durationMs": 3344
              },
              {
                "name": "[a11y] data-testid=\"sw-figma-size-m-selected-false\" — zero serious/critical",
                "status": "passed",
                "durationMs": 3264
              },
              {
                "name": "[a11y] data-testid=\"sw-figma-appearance-primary-on\" — zero serious/critical",
                "status": "passed",
                "durationMs": 2336
              },
              {
                "name": "[a11y] data-testid=\"sw-figma-accent-primary-on\" — zero serious/critical",
                "status": "passed",
                "durationMs": 3454
              },
              {
                "name": "[a11y] data-testid=\"sw-figma-disabled-true-on\" — zero serious/critical",
                "status": "passed",
                "durationMs": 3738
              },
              {
                "name": "[a11y] data-testid=\"sw-figma-readonly-true-on\" — zero serious/critical",
                "status": "passed",
                "durationMs": 3303
              },
              {
                "name": "[a11y] data-testid=\"sw-figma-selected-controlled\" — zero serious/critical",
                "status": "passed",
                "durationMs": 3826
              },
              {
                "name": "[a11y] Section 508 tag run — zero serious/critical",
                "status": "passed",
                "durationMs": 3127
              },
              {
                "name": "[a11y] axe label rule — showcase bands, zero serious/critical",
                "status": "passed",
                "durationMs": 2591
              },
              {
                "name": "[a11y] ARIA validity rules — zero serious/critical",
                "status": "passed",
                "durationMs": 3031
              },
              {
                "name": "[a11y] axe name rules — showcase bands, zero serious/critical",
                "status": "passed",
                "durationMs": 2947
              },
              {
                "name": "[a11y] page lang on <html>",
                "status": "passed",
                "durationMs": 2651
              },
              {
                "name": "[a11y] Viewport 320px — horizontal overflow check per showcase band",
                "status": "passed",
                "durationMs": 3176
              },
              {
                "name": "[a11y] 200% zoom — showcase switches remain visible",
                "status": "passed",
                "durationMs": 1726
              },
              {
                "name": "[a11y] Tab reaches a focusable control",
                "status": "passed",
                "durationMs": 2635
              },
              {
                "name": "[a11y] no keyboard trap (Tab cycle advances)",
                "status": "passed",
                "durationMs": 2850
              },
              {
                "name": "[a11y] focused element shows outline or box-shadow",
                "status": "passed",
                "durationMs": 2776
              },
              {
                "name": "[a11y] focus order — Tab visits multiple distinct targets",
                "status": "passed",
                "durationMs": 2583
              },
              {
                "name": "[a11y] Theme toggle activates with Enter when focused",
                "status": "passed",
                "durationMs": 2397
              },
              {
                "name": "[a11y] Theme toggle activates with Space when focused",
                "status": "passed",
                "durationMs": 2091
              },
              {
                "name": "[a11y] Switch QA page has no critical or serious axe violations",
                "status": "failed",
                "durationMs": 4913,
                "error": "An icon is exposed as an image (role=\"img\") without a name. Decorative icons should be aria-hidden; meaningful icons need aria-label."
              },
              {
                "name": "[a11y] section \"switch-figma-default\" has no critical or serious axe violations",
                "status": "passed",
                "durationMs": 4424,
                "componentBand": "switch-figma-default"
              },
              {
                "name": "[a11y] section \"switch-figma-size-selected\" has no critical or serious axe violations",
                "status": "passed",
                "durationMs": 4804,
                "componentBand": "switch-figma-size-selected"
              },
              {
                "name": "[a11y] section \"switch-figma-appearance\" has no critical or serious axe violations",
                "status": "passed",
                "durationMs": 4726,
                "componentBand": "switch-figma-appearance"
              },
              {
                "name": "[a11y] section \"switch-figma-accent\" has no critical or serious axe violations",
                "status": "passed",
                "durationMs": 4016,
                "componentBand": "switch-figma-accent"
              },
              {
                "name": "[a11y] section \"switch-figma-disabled\" has no critical or serious axe violations",
                "status": "passed",
                "durationMs": 3028,
                "componentBand": "switch-figma-disabled"
              },
              {
                "name": "[a11y] section \"switch-figma-readonly\" has no critical or serious axe violations",
                "status": "passed",
                "durationMs": 4193,
                "componentBand": "switch-figma-readonly"
              },
              {
                "name": "[a11y] section \"switch-figma-selected-interactive\" has no critical or serious axe violations",
                "status": "passed",
                "durationMs": 4315,
                "componentBand": "switch-figma-selected-interactive"
              },
              {
                "name": "[a11y] Default band switch has role switch and accessible name",
                "status": "passed",
                "durationMs": 3466
              },
              {
                "name": "[a11y] Disabled switch is not enabled",
                "status": "passed",
                "durationMs": 2551
              },
              {
                "name": "[a11y] Read-only switch exposes aria-readonly",
                "status": "passed",
                "durationMs": 3024
              }
            ],
            "axe": {
              "violations": [
                {
                  "id": "color-contrast",
                  "impact": "serious",
                  "description": "Ensure the contrast between foreground and background colors meets WCAG 2 AA minimum contrast ratio thresholds",
                  "helpUrl": "https://dequeuniversity.com/rules/axe/4.11/color-contrast?application=playwright",
                  "nodes": 3
                },
                {
                  "id": "role-img-alt",
                  "impact": "serious",
                  "description": "Ensure [role=\"img\"] elements have alternative text",
                  "helpUrl": "https://dequeuniversity.com/rules/axe/4.11/role-img-alt?application=playwright",
                  "nodes": 1
                }
              ]
            }
          },
          "functional": {
            "suite": "functional",
            "passed": 54,
            "failed": 1,
            "skipped": 0,
            "logs": [
              "55 test(s) in Playwright report for functional."
            ],
            "errors": [
              "[fn] 1.3 — every data-section is visible: Tearing down \"context\" exceeded the test timeout of 30000ms."
            ],
            "cases": [
              {
                "name": "[fn] 1.1 — no console errors on playground load",
                "status": "passed",
                "durationMs": 4176
              },
              {
                "name": "[fn] 1.2 — every playground data-testid is visible",
                "status": "passed",
                "durationMs": 3475
              },
              {
                "name": "[fn] 1.3 — every data-section is visible",
                "status": "failed",
                "durationMs": 33909,
                "error": "Tearing down \"context\" exceeded the test timeout of 30000ms."
              },
              {
                "name": "[fn] 2.1 — size S/M/L wrappers expose data-size",
                "status": "passed",
                "durationMs": 1977
              },
              {
                "name": "[fn] 2.1 — appearance primary-off sets data-appearance on switch",
                "status": "passed",
                "durationMs": 1081
              },
              {
                "name": "[fn] 2.1 — selected-true cells are checked by default",
                "status": "passed",
                "durationMs": 1005
              },
              {
                "name": "[fn] 2.2 — Size scaling — S < M < L track width",
                "status": "passed",
                "durationMs": 927
              },
              {
                "name": "[fn] 3.1 — click toggles aria-checked on default switch",
                "status": "passed",
                "durationMs": 4293
              },
              {
                "name": "[fn] 3.2 — disabled switch does not toggle on click",
                "status": "passed",
                "durationMs": 2884
              },
              {
                "name": "[fn] 3.3 — readOnly switch does not toggle on click",
                "status": "passed",
                "durationMs": 2609
              },
              {
                "name": "[fn] 3.4 — click outside removes focus from switch",
                "status": "passed",
                "durationMs": 3671
              },
              {
                "name": "[fn] 4.1 — Tab reaches default switch",
                "status": "passed",
                "durationMs": 2553
              },
              {
                "name": "[fn] 4.2 — Enter toggles focused default switch",
                "status": "passed",
                "durationMs": 2217
              },
              {
                "name": "[fn] 4.4 — Arrow keys (N/A)",
                "status": "passed",
                "durationMs": 1712
              },
              {
                "name": "[fn] 4.5 — Home and End (N/A)",
                "status": "passed",
                "durationMs": 3904
              },
              {
                "name": "[fn] 4.6 — Escape (N/A)",
                "status": "passed",
                "durationMs": 2077
              },
              {
                "name": "[fn] 4.7 — Tab through page without keyboard trap",
                "status": "passed",
                "durationMs": 2249
              },
              {
                "name": "[fn] 5.1 — click focuses default switch",
                "status": "passed",
                "durationMs": 2618
              },
              {
                "name": "[fn] 5.2 — focus ring visible on default switch",
                "status": "passed",
                "durationMs": 2816
              },
              {
                "name": "[fn] 5.5 — autoFocus (N/A)",
                "status": "passed",
                "durationMs": 2106
              },
              {
                "name": "[fn] 6.1 — default switch starts unchecked",
                "status": "passed",
                "durationMs": 2313
              },
              {
                "name": "[fn] 6.2 — appearance-on cells render checked",
                "status": "passed",
                "durationMs": 3544
              },
              {
                "name": "[fn] 6.3 — disabled switch is not enabled",
                "status": "passed",
                "durationMs": 2605
              },
              {
                "name": "[fn] 6.4 — readOnly switch exposes aria-readonly",
                "status": "passed",
                "durationMs": 2179
              },
              {
                "name": "[fn] 6.5 — Error state (N/A)",
                "status": "passed",
                "durationMs": 1718
              },
              {
                "name": "[fn] 6.6 — Loading state (N/A)",
                "status": "passed",
                "durationMs": 3834
              },
              {
                "name": "[fn] 7.1 — start/end slots (N/A)",
                "status": "passed",
                "durationMs": 2448
              },
              {
                "name": "[fn] 8.1 — click toggles off → on → off with aria-checked",
                "status": "passed",
                "durationMs": 2031
              },
              {
                "name": "[fn] 8.2 — Single select (N/A)",
                "status": "passed",
                "durationMs": 2603
              },
              {
                "name": "[fn] 8.3 — Indeterminate (N/A)",
                "status": "passed",
                "durationMs": 2612
              },
              {
                "name": "[fn] 9.1 — Typing (N/A)",
                "status": "passed",
                "durationMs": 1359
              },
              {
                "name": "[fn] 10.1 — accent prop renders accent on/off pair",
                "status": "passed",
                "durationMs": 1024
              },
              {
                "name": "[fn] 11.3 — Progress value (N/A)",
                "status": "passed",
                "durationMs": 902
              },
              {
                "name": "[fn] 12.1 — fullWidth (N/A)",
                "status": "passed",
                "durationMs": 1095
              },
              {
                "name": "[fn] 12.2 — visible at 320px viewport",
                "status": "passed",
                "durationMs": 1880
              },
              {
                "name": "[fn] 12.2 — visible at 1440px viewport",
                "status": "passed",
                "durationMs": 1693
              },
              {
                "name": "[fn] 12.3 — size band rows layout horizontally",
                "status": "passed",
                "durationMs": 909
              },
              {
                "name": "[fn] Smoke — Page heading reads “Switch”",
                "status": "passed",
                "durationMs": 879
              },
              {
                "name": "[fn] Smoke — Default switch is visible",
                "status": "passed",
                "durationMs": 893
              },
              {
                "name": "[fn] Smoke — Appearance primary-off switch is visible",
                "status": "passed",
                "durationMs": 945
              },
              {
                "name": "[fn] shows Switch page heading",
                "status": "passed",
                "durationMs": 4326
              },
              {
                "name": "[fn] theme toggle updates label",
                "status": "passed",
                "durationMs": 2655
              },
              {
                "name": "[fn] scenario and report tabs are present",
                "status": "passed",
                "durationMs": 2400
              },
              {
                "name": "[fn] figma validation tab mounts grid",
                "status": "passed",
                "durationMs": 3550
              },
              {
                "name": "[fn] renders switch: sw-figma-default",
                "status": "passed",
                "durationMs": 2525
              },
              {
                "name": "[fn] renders switch: sw-figma-size-s-selected-false",
                "status": "passed",
                "durationMs": 2303
              },
              {
                "name": "[fn] renders switch: sw-figma-size-s-selected-true",
                "status": "passed",
                "durationMs": 1479
              },
              {
                "name": "[fn] renders switch: sw-figma-appearance-primary-off",
                "status": "passed",
                "durationMs": 2920
              },
              {
                "name": "[fn] renders switch: sw-figma-accent-primary-off",
                "status": "passed",
                "durationMs": 2473
              },
              {
                "name": "[fn] renders switch: sw-figma-disabled-false",
                "status": "passed",
                "durationMs": 1935
              },
              {
                "name": "[fn] renders switch: sw-figma-readonly-true-off",
                "status": "passed",
                "durationMs": 1852
              },
              {
                "name": "[fn] renders switch: sw-figma-selected-controlled",
                "status": "passed",
                "durationMs": 4319
              },
              {
                "name": "[fn] default switch toggles on click",
                "status": "passed",
                "durationMs": 2707
              },
              {
                "name": "[fn] controlled switch toggles via click",
                "status": "passed",
                "durationMs": 2368
              },
              {
                "name": "[fn] Space toggles focused default switch",
                "status": "passed",
                "durationMs": 3023
              }
            ]
          },
          "performance": {
            "suite": "performance",
            "passed": 0,
            "failed": 0,
            "skipped": 0,
            "logs": [
              "Performance suite is not executed in apps/qa-playground switch Playwright bundle."
            ],
            "errors": []
          }
        }
      }
    }
  ]
}